{"mix":2075,"rounds":[[{"category":"THE PHONE","comments":"","clues":[{"text":"Marshmallow is the name of the 6.0 version of this operating system that powers millions of smartphones","response":"Android"},{"text":"E.T. would enjoy the USO program called Operation this 2-word phrase, giving intl. calling cards to service members","response":"Phone Home"},{"text":"Jamie Fuller created an app called this \"Dialer\" that lets you reach out &amp; touch someone like it was the '70s","response":"the rotary telephone"},{"text":"In \"Pillow Talk\" Doris Day &amp; Rock Hudson share this kind of multi-user line &amp; romantic confusion ensues","response":"a party line"},{"text":"In 1878 George Coy used teapot lids to build the first of these panels used by operators &amp; soon they were \"lighting up\"","response":"a switchboard"}],"originalDate":"2016-06-07"},{"category":"PRO SPORTS TEAM NAME CHANGES","comments":"","clues":[{"text":"In 1932 the Brooklyn Robins changed their name back to this","response":"the Brooklyn Dodgers"},{"text":"In 2014 these Charlotte NBA felines became the Hornets","response":"the Bobcats"},{"text":"A move from Texas to Tennessee earned an NFL team this new name","response":"the Titans"},{"text":"\"Stockings\" was once part of the name of this oldest team in the NL Central Division","response":"the Cincinnati Reds"},{"text":"In 2007 an exorcism was performed on the name of this Florida team","response":"the Tampa Bay Rays"}],"originalDate":"2016-06-06"},{"category":"NATIONAL PARKS","comments":"","clues":[{"text":"Mount Rainier is in this coastal state","response":"Washington"},{"text":"Biscayne is in this coastal state","response":"Florida"},{"text":"Evil-sounding park in southwestern South Dakota","response":"the Badlands"},{"text":"Shenandoah in Virginia is in this \"Ridge\", part of the Appalachians","response":"the Blue Ridge"},{"text":"State where you'll find (the non-southern) Acadia","response":"Maine"}],"originalDate":"2016-06-06"},{"category":"CROSSWORD CLUES \"P\"","comments":"(Alex: Highlighted because each correct response will begin with that letter.)","clues":[{"text":"Italian pie joint<br>(8)","response":"pizzeria"},{"text":"Cologne cousin<br>(7)","response":"perfume"},{"text":"Dry period in U.S. history<br>(11)","response":"Prohibition"},{"text":"Big shrimp<br>(5)","response":"prawn"},{"text":"Step-counting gadget<br>(9)","response":"pedometer"}],"originalDate":"2016-06-06"},{"category":"FROM THE FOREIGN","comments":"","clues":[{"text":"German gave us this word for a child prodigy","response":"<i>Wunderkind</i>"},{"text":"From the Arabic for \"zero\", it can mean zero or a coded message","response":"cipher"},{"text":"This word for income is from the French for \"return\"","response":"revenue"},{"text":"You don't have to be part of it to know \"intelligentsia\" is from this language","response":"Russian"},{"text":"This 5-letter word from the Dutch is sailors' talk for \"stop that!\"","response":"avast"}],"originalDate":"2016-06-06"},{"category":"ELLIS ISLAND","comments":"","clues":[{"text":"In 1890 Ellis Island doubled in size by using ships' ballast &amp; dirt from the building of this transportation system","response":"the New York subway"},{"text":"During WWI, about 1,800 citizens of this country were seized at ports &amp; interned at Ellis Island before being deported","response":"Germany"},{"text":"In 1965 Lyndon Johnson issued a proclamation making Ellis Island a part of this national monument","response":"the Statue of Liberty"},{"text":"While attending law school, this future NYC mayor known as \"The Little Flower\" served as an interpreter on the island","response":"LaGuardia"},{"text":"On January 1, 1892 15-year-old Annie Moore from this largest Irish county became the first processed &amp; that's no blarney","response":"County Cork"}],"originalDate":"2016-06-06"}],[{"category":"ALL KINDS OF DRAMA","comments":"","clues":[{"text":"In its original sense, \"comedy\" didn't mean that the play was necessarily funny but that it would end this way","response":"happily"},{"text":"As the name suggests, these entertainments like 1612's \"Love Restored\" involved players with covered faces","response":"masques (masquerades accepted)"},{"text":"Emphasizing violence &amp; horror, Grand Guignol plays of the 19th century took their name from a theater in this city","response":"Paris"},{"text":"5-letter name for a laugh-fest using improbable, complicated plots &amp; larger-than-life characters","response":"farce"},{"text":"The 3 Ms of medieval drama were the mystery play, the morality play &amp; this one, aka a saint's play","response":"a miracle play"}],"originalDate":"2016-06-06"},{"category":"THE 1950s","comments":"","clues":[{"text":"A 1952 article in Reader's Digest, \"Cancer by the Carton\", warned against this","response":"smoking"},{"text":"These 2 states were admitted to the Union in the 1950s","response":"Alaska & Hawaii"},{"text":"His support waned after his wife Evita died in 1952 &amp; he was forced into exile in 1955","response":"(Juan) Peron"},{"text":"In 1958 this U.S. atomic sub sailed under the North Pole","response":"Nautilus"},{"text":"17-year-old Hussein took over this country's throne in 1953 after his father, Talal, was removed","response":"Jordan"}],"originalDate":"1994-11-09"},{"category":"BROADWAY MUSICAL STARS","comments":"","clues":[{"text":"Barbra Streisand was nominated for a 1964 Tony for \"Funny Girl\" but lost to this star of \"Hello Dolly!\"","response":"Carol Channing"},{"text":"He was working as a television director when he was hired to play the King in \"The King and I\" in 1951","response":"Yul Brynner"},{"text":"This lovely British actress played Guenevere in the original 1960 production of \"Camelot\"","response":"Julie Andrews"},{"text":"Ken Howard played Thomas Jefferson in this Tony-winning musical","response":"<i>1776</i>"},{"text":"In 1993 Richard Chamberlain starred as Professor Henry Higgins in a revival of this musical","response":"<i>My Fair Lady</i>"}],"originalDate":"1994-11-09"},{"category":"MUSEUMS","comments":"","clues":[{"text":"This soup company in Camden, N.J. has a museum of soup tureens, bowls &amp; ladles","response":"Campbell's"},{"text":"The National Portrait Gallery is a part of this Washington, D.C. museum complex","response":"Smithsonian"},{"text":"Memorabilia of this aviatrix are displayed at the County Historical Museum in her hometown, Atchison, Kan.","response":"Amelia Earhart"},{"text":"The University of Pittsburgh has a library &amp; museum devoted to this composer of \"Oh! Susanna\"","response":"(Stephen) Foster"},{"text":"The Topkapi Palace, in this city on the Bosporus, includes several museums","response":"Istanbul"}],"originalDate":"1994-11-09"},{"category":"MYTHOLOGY","comments":"","clues":[{"text":"I'ts the Latinized name of the Greek hero Heracles","response":"Hercules"},{"text":"Gordius, of Gordian knot fame, was the father of this man with the golden touch","response":"Midas"},{"text":"The underworld was guarded by Cerberus, a 3-headed type of this animal","response":"dog"},{"text":"Legend says that this woman, a cause of the Trojan War, was later hanged on Rhodes","response":"Helen (of Troy)"},{"text":"This bull-headed monster was the son of Pasiphae, the wife of King Minos","response":"Minotaur"}],"originalDate":"1994-11-09"},{"category":"IS THERE A DOCTOR IN THE HOUSE?","comments":"","clues":[{"text":"Imhotep of this ancient civilization is honored as the first doctor known by name","response":"Egypt"},{"text":"In the 1870s John M. Woodworth became the first person to hold this post now held by Dr. Joycelyn Elders","response":"Surgeon General"},{"text":"The \"maneuver\" he developed is designed to aid drowning victims as well as choking victims","response":"Heimlich"},{"text":"The Army medical center named for this doctor opened in Washington, D.C. in 1909","response":"Walter Reed"},{"text":"This doctor &amp; humanitarian's work in Africa kept him from picking up his 1952 Nobel Peace Prize","response":"Albert Schweitzer"}],"originalDate":"1994-11-09"}],{"category":"1970s SITCOMS","text":"A warning on early episodes said this show \"seeks to throw a humorous spotlight on our frailties, prejudices and concerns\"","response":"<i>All in the Family</i>"}]}