{"mix":3205,"rounds":[[{"category":"WHERE THE WILD THINGS ARE","comments":"","clues":[{"text":"The split-jawed type of this constricting snake is native to the islands of Mauritius","response":"a boa"},{"text":"The Amur tiger, aka this tiger, ranges from southeastern Russia to northern China","response":"the Siberian tiger"},{"text":"Indonesia's the place to see this ape whose name comes from Malaysian for \"person of the forest\"","response":"an orangutan"},{"text":"Go deep (though not 20,000 leagues) to find Architeuthis dux, this rarely seen cephalopod","response":"the giant squid"},{"text":"We have good hope you can tell us this alternate name for the African buffalo (it lives in Africa, by the way)","response":"the Cape buffalo"}],"originalDate":"2011-01-17"},{"category":"NOW WE ARE SIX","comments":"","clues":[{"text":"Enacted in 1791, it guarantees the right to a trial by jury","response":"the Sixth Amendment"},{"text":"Of the 6 prophets of Islam, Muhammad was the last &amp; this early biblical guy was the first","response":"Adam"},{"text":"It's the sixth letter in the Greek alphabet, &amp; it's similar to the last letter in ours","response":"zeta"},{"text":"The 6 schools of Hindu philosophy include Mimamsa, Vedanta &amp; this one, usually associated with serene exercise","response":"Yoga"},{"text":"A sexangle is another name for this geometric figure, from the Greek for \"six\"","response":"a hexagon"}],"originalDate":"2011-01-17"},{"category":"CURIOUS","comments":"","clues":[{"text":"SpongeBob tells Gary, \"Curiosity salted the snail\", a play on this feline proverb","response":"Curiosity killed the cat"},{"text":"\"Curiosity\" was shortened to this word for an unusual artifact","response":"a curio"},{"text":"To look into what's none of your business, or to open a paint can","response":"to pry"},{"text":"Spider-Man's alter ego Peter could be called this 2-word phrase meaning a busybody","response":"a nosy parker"},{"text":"A Latin word for \"to ask\" gave us this adjective meaning curious for knowledge","response":"inquisitive"}],"originalDate":"2011-01-17"},{"category":"DENZEL WASHINGTON FILMS","comments":"","clues":[{"text":"Tom Hanks' Pennsylvania lawyer","response":"<i>Philadelphia</i>"},{"text":"A member of the 54th regiment of the Massachusetts Volunteer Infantry","response":"<i>Glory</i>"},{"text":"A NYC subway dispatcher","response":"<i>The Taking of Pelham 1 2 3</i>"},{"text":"A man who has memorized the Bible","response":"<i>The Book of Eli</i>"},{"text":"A Mexico City bodyguard looking for revenge","response":"<i>Man on Fire</i>"}],"originalDate":"2011-01-17"},{"category":"A WOMAN'S PLACE IS IN THE HOUSE","comments":"","clues":[{"text":"In 1983 Barbara Boxer punched in as a congresswoman from this state","response":"California"},{"text":"In 1978 she was elected to the house from N.Y.'s Ninth District; in 1984 she was not elected vice president","response":"Geraldine Ferraro"},{"text":"She gently drifted down from Maine to D.C. in 1979; she's in the Senate now","response":"(Olympia) Snowe"},{"text":"In 2002 this Florida Secretary of State published \"Center of the Storm\" &amp; was elected to Congress","response":"Katherine Harris"},{"text":"Former Rep. Debbie Stabenow took a stab &amp; is now a U.S. senator from this state","response":"Michigan"}],"originalDate":"2011-01-17"},{"category":"WEAPONRY","comments":"","clues":[{"text":"An 1897 officer's knife, aka this, had a corkscrew &amp; second blade; no one's neutral when holding one","response":"a Swiss Army knife"},{"text":"A spray used in self-defense, or a spiked, club-like item to do even more damage","response":"a mace"},{"text":"This sword from some royal tales is said to derive from Caladbolg, a weapon of Irish legend","response":"Excalibur"},{"text":"It's an alphanumeric Soviet assault rifle with a cyclic firing rate of 600 rounds per minute","response":"an AK-47"},{"text":"This flat, angular bomber the Air Force unveiled in 1988 can really fly under the radar<span class=\"nobreak\">--</span>or through it","response":"a Stealth Bomber (B-2)"}],"originalDate":"2011-01-17"}],[{"category":"FOOD WORDS &amp; PHRASES","comments":"","clues":[{"text":"Idiomatically, the stick is the coercion while this vegetable is the reward","response":"the carrot"},{"text":"2 basic foods are joined together in this adjective for a type of pickle or for a basic need","response":"bread & butter"},{"text":"A person who wears tight jeans that cause flab to spill out over the waistband is said to have this","response":"a muffin top"},{"text":"California car buyers are protected by the Tanner Consumer Protection Act, known by this alliterative name","response":"the Lemon Law"},{"text":"This 1928 Republican campaign slogan originated with a hope that Henry IV had for French peasants","response":"\"A chicken in every pot\""}],"originalDate":"2011-01-17"},{"category":"ROCK &amp; ROLL HALL OF FAME","comments":"","clues":[{"text":"Handwritten lyrics on display include Chuck Berry's \"School Days\" &amp; his \"Purple Haze\"","response":"Jimi Hendrix"},{"text":"Jann Wenner, editor &amp; publisher of this magazine, is 1 of 26 on the Hall's board of trustees","response":"<i>Rolling Stone</i>"},{"text":"Known for playing Ziggy Stardust, he donated a plaster cast of his face for the mannequins representing him","response":"David Bowie"},{"text":"He said, \"In designing this building, it was my intention to echo the energy of rock and roll\"","response":"I.M. Pei"},{"text":"Equipment used by Sam Phillips to record Elvis Presley is on exhibit in a tribute to this record company","response":"Sun"}],"originalDate":"1996-09-03"},{"category":"WORLD HISTORY","comments":"","clues":[{"text":"In 1785 this future French emperor graduated from military school in Paris, 42nd in his class of 58","response":"Napoleon"},{"text":"Barons &amp; churchmen drew up this 1215 document to reduce the power of England's King John","response":"The <i>Magna Carta</i>"},{"text":"In 1519 he &amp; his men landed at Tabasco &amp; began the Spanish conquest of Mexico","response":"Cortes"},{"text":"In 1936 Italy conquered this Ethiopian capital &amp; Haile Selassie fled to Great Britain","response":"Addis Ababa"},{"text":"In this mid-1930s this U.S. naval officer chartered the Edsel Ford mountains in Antarctica","response":"(Admiral) Byrd"}],"originalDate":"1996-09-03"},{"category":"FASHION","comments":"","clues":[{"text":"Lumberjack shirts &amp; kilts feature these designs","response":"tartans (or plaids)"},{"text":"What's considered the finest cotton in the world is grown in &amp; named for this country","response":"Egypt"},{"text":"Worn by South American Indians for centuries, it's square, has a hole in the middle &amp; doubles as a blanket","response":"a poncho"},{"text":"Men's tails are also known by this longer, avian name","response":"swallow-tails"},{"text":"Famous for their seeksucker suits, these New York brothers made the frock coat Lincoln wore to Ford's Theatre","response":"the Brooks Brothers"}],"originalDate":"1996-09-03"},{"category":"BIBLICAL FIRSTS","comments":"","clues":[{"text":"He's the first person in the Bible to build a ship","response":"Noah"},{"text":"God's first instructions to human beings were \"be fruitful and\" do this","response":"to multiply"},{"text":"This strongman told the first riddle; it concerned a honey-filled lion","response":"Samson"},{"text":"Rachel is the first shepherdess mentioned &amp; he's the first shepherd","response":"Abel"},{"text":"This disguised man was the first person to kiss someone in the Bible; he kissed his father","response":"Jacob"}],"originalDate":"1996-09-03"},{"category":"NOTORIOUS","comments":"","clues":[{"text":"He was an employee of the Texas School Book Depository when he shot JFK from its 6th floor","response":"Oswald"},{"text":"He established a commune for his \"family\" on the Spahn Ranch outside Los Angeles","response":"(Charles) Manson"},{"text":"Alvin \"Creepy\" Karpis holds the record for time served on this \"rock\" &mdash; 28 years","response":"Alcatraz"},{"text":"The St. Valentine's Day Massacre broke the power of this Chicago gangster nicknamed \"Bugs\"","response":"George \"Bugsy\" Moran"},{"text":"Ramon Mercader, who killed this Russian in Mexico in 1940, died in Havana in 1978","response":"Trotsky"}],"originalDate":"1996-09-03"}],{"category":"BRITISH LITERARY CHARACTERS","text":"In an 1887 novel this narrator's old wartime injury is in his shoulder; in an 1890 novel by the same author, it's in his leg","response":"Dr. Watson"}]}