{"mix":3600,"rounds":[[{"category":"VEGAS FILMS","comments":"","clues":[{"text":"In \"Casino\" he played Ace Rothstein, the mobster who ran The Tangiers","response":"(Robert) De Niro"},{"text":"He directed the 2001 Vegas caper film \"Ocean's Eleven\"","response":"(Steven) Soderbergh"},{"text":"The title of this 2008 Cameron Diaz-Ashton Kutcher film was inspired by a Sin City slogan","response":"<i>What Happens in Vegas</i>"},{"text":"One review said this 1995 Elizabeth Berkley film was \"'42nd Street' meets 'All About Eve' meets soft-core porn\"","response":"<i>Showgirls</i>"},{"text":"In a 2003 film he played \"The Cooler\", a Vegas casino's gambling jinx","response":"William H. Macy"}],"originalDate":"2009-03-24"},{"category":"FLOORING","comments":"","clues":[{"text":"Grout &amp; a special saw are tools for installing this type of floor","response":"tile"},{"text":"Also the surface of bulletin boards, this material makes warm, sound-insulating flooring","response":"cork"},{"text":"This durable material almost synonymous with mid-20th c. flooring was patented in 1863","response":"linoleum"},{"text":"In forestry, it's a synonym for \"dicot\"; in real estate ads, it makes mouths water when seen before \"floors\"","response":"hardwood"},{"text":"1 letter off from \"flat stones\", they make good flooring for your castle","response":"flagstones"}],"originalDate":"2009-03-24"},{"category":"REBELLIONS: SHAYS' &amp; WHISKEY","comments":"","clues":[{"text":"Both Shays' Rebellion &amp; the Whiskey Rebellion were protests against these","response":"taxes"},{"text":"Shays' Rebellion in this state in 1786-87 included an attack on the Springfield armory","response":"Massachusetts"},{"text":"This Treasury Sec. helped form, &amp; then tagged along with, the army sent to suppress the Whiskey Rebellion","response":"Hamilton"},{"text":"Though put down swiftly, Shays' Rebellion exposed the military weakness of this 1781 document","response":"the Articles of Confederation"},{"text":"Thousands of Whiskey Rebels marched to \"The Point\" in this Penn. city, but were persuaded not to burn the town","response":"Pittsburgh"}],"originalDate":"2009-03-24"},{"category":"POETIC WORDS","comments":"","clues":[{"text":"E'er is a poetic form of this adverb","response":"ever"},{"text":"E'en is a poetic form of this adverb","response":"even"},{"text":"In \"To Celia\", this possessive case of thou precedes the word \"eyes\"","response":"thine"},{"text":"\"L'allegro\" by Milton uses this 4-letter word for a deep shade of black, a shortening of the name of a wood","response":"ebon"},{"text":"A poem by Robert Burns taught us that \"gang aft\" this means \"often go wrong\"","response":"agley"}],"originalDate":"2009-03-24"},{"category":"TOUGH CAPITAL CITIES","comments":"","clues":[{"text":"One of the \"Stan\"s:<br>Tashkent","response":"Uzbekistan"},{"text":"Island country in the Indian ocean:<br>Port Louis","response":"Mauritius"},{"text":"A former Soviet republic: Chisinau","response":"Moldova"},{"text":"In western Africa:<br>Yamoussoukro","response":"Cote d'Ivoire (The Ivory Coast)"},{"text":"In the Pacific:<br>Honiara","response":"the Solomon Islands"}],"originalDate":"2009-03-24"},{"category":"THINK YOU KNOW BASEBALL?","comments":"","clues":[{"text":"He hit the first home run in All-Star game history (take a wild guess)","response":"Babe Ruth"},{"text":"Their home parks have included the Union Grounds, Crosley Field &amp; Riverfront Stadium","response":"the (Cincinnati) Reds"},{"text":"The New York Yankees have won 26 World Series titles; these N.L. birds are a distant second, with 10","response":"the Cardinals"},{"text":"Researchers have knocked a point off his record lifetime batting average, reducing it to .366","response":"(Ty) Cobb"},{"text":"\"Avian\" nickname of 1960s reliever Phil Regan, notorious for \"stealing\" wins from starting pitchers","response":"\"The Vulture\""}],"originalDate":"2009-03-24"}],[{"category":"CHAMPIONS OF TOURNAMENTS","comments":"","clues":[{"text":"In 2006 in Berlin, Italy won this sports tourney by beating France, 1-1 (technically, that was the final score)","response":"the World Cup"},{"text":"As world champ of this Parker Bros. game, Antonio Fernandez won $15,140, the total amount of \"cash\" in the game","response":"<i>Monopoly</i>"},{"text":"In 2007 Nigel Richards took home $15,000 as the letter-perfect world champ of this Hasbro game","response":"<i>Scrabble</i>"},{"text":"In 2007 16-year-old Ayan Tariq bested 31 others to win $100,000 playing this title ex-coach's football video game","response":"(John) Madden"},{"text":"In 1972 \"Amarillo Slim\" won this annual event","response":"the World Series of Poker"}],"originalDate":"2009-03-24"},{"category":"MEET THE BEADLES","comments":"","clues":[{"text":"\"Beadle\", meaning a minor official, comes from Middle English for one of these old-time announcer guys<span class=\"nobreak\">--</span>hark!","response":"a herald"},{"text":"In hunting season, Beadle County, South Dakota is a bad place to be a ring-necked one of these, the state bird","response":"a pheasant"},{"text":"In this Sondheim musical, Beadle Bamford gets sliced up for pie filling (don't worry, he wasn't a good guy)","response":"<i>Sweeney Todd</i>"},{"text":"George Beadle won a Nobel Prize for studying the genetics of a bread type of this fuzzy fungus","response":"mold"},{"text":"In this author's \"Night\", Moshe the Beadle warns the Jews of Sighet about the looming holocaust, but they don't listen","response":"(Elie) Wiesel"}],"originalDate":"2009-03-24"},{"category":"ADJECTIVES TO USE IN VEGAS","comments":"","clues":[{"text":"Your bold, audacious bets could be called this, perhaps from a blend of \"bold\" &amp; \"audacious\"","response":"bodacious"},{"text":"I expect to be treated like a VIP, so remember that the \"I\" stands for this adjective","response":"important"},{"text":"Also a type of fabric, this synonym for lavish describes my suite (&amp; it rhymes with lush)","response":"plush"},{"text":"I must see the \"O\" show<span class=\"nobreak\">--</span>it boasts this type of swimming, also an artistic Olympic event","response":"synchronized"},{"text":"From the Latin for \"great-souled\", it will describe your immense generosity after you win big bucks","response":"magnanimous"}],"originalDate":"2009-03-24"},{"category":"MUSICALS BY PLOT","comments":"","clues":[{"text":"Rock &amp; roll &amp; dancing are forbidden in small puritanical town; rebellious Ren to the rescue","response":"<i>Footloose</i>"},{"text":"Crusading Houston radio host exposes Chicken Ranch","response":"<i>The Best Little Whorehouse in Texas</i>"},{"text":"\"Prince of Humbug\" creates freak show, signs Jenny Lind","response":"<i>Barnum</i>"},{"text":"Charlemagne's son leads a revolution against his dad","response":"<i>Pippin</i>"},{"text":"Slave tries to win freedom by helping his master earn the love of a courtesan; when in Rome…","response":"<i>A Funny Thing Happened on the Way to the Forum</i>"}],"originalDate":"2009-03-23"},{"category":"FASHION FORWARD &amp; BACKWARD","comments":"","clues":[{"text":"Popular in the '50s the slim skirts named for this writing implement have become chic again","response":"pencil skirts"},{"text":"retro-housewife.com calls a '70s-style tunic in a '60s print a \"mippie\", a blend of mod &amp; this word","response":"hippie"},{"text":"This couturiere's iconic collarless jacket of 1954 is still part of her line today","response":"Coco Chanel"},{"text":"Too bad you didn't buy a Birkin one of these in the '80s; now the waiting list can take years","response":"a handbag"},{"text":"On or off a yacht, this neckline whose name is French for \"boat\" has been stylish for decades","response":"bateau"}],"originalDate":"2009-03-23"},{"category":"MEDICINE SHOW","comments":"","clues":[{"text":"Breathe Right strips alleviate this sleeping noise, but became huge when Jerry Rice used them on the field","response":"snoring"},{"text":"The bronchodilator Albuterol helps relieve this condition, from the Greek for \"panting\"","response":"asthma"},{"text":"Nexium fights acid reflux, which also goes by this name, though it has nothing to do with the organ","response":"heartburn"},{"text":"Atorvastatin is the generic name of this cholesterol drug from Pfizer","response":"Lipitor"},{"text":"This medicine is sold under the brand names Feverall &amp; Tylenol","response":"acetaminophen"}],"originalDate":"2009-03-23"}],{"category":"SPORTS","text":"This classic race was first won by Ray Harroun on May 30, 1911","response":"the Indianapolis 500"}]}