{"showNumber":1566,"airDate":"1991-05-27","comments":"","rounds":[[{"category":"MUSIC","comments":"","clues":[{"text":"When the abbreviation \"o.p.\" is followed by a number, op. stands for this","response":"opus"},{"text":"In German, these holiday songs are known as Weihnachtslieder","response":"Christmas carols"},{"text":"Tchaikovsky's \"Hamlet\" is a \"tone\" one of these","response":"a tone poem"},{"text":"This city's controversial new opera house opened in '90 with a production of \"The Trojans\" by Berlioz","response":"Paris"},{"text":"The George M. Cohan song that ends with \"I'll be there, ere long\"","response":"\"Give My Regards To Broadway\""}]},{"category":"SPORTS","comments":"","clues":[{"text":"In bowling it's getting all the pins down at once without any to \"spare\"","response":"a strike"},{"text":"The sport in which you carry your projectiles in a quiver","response":"archery"},{"text":"A hot dog can shoot the tube in this sport","response":"surfing"},{"text":"A twist,<br>a gainer<br>or a swan","response":"a dive"},{"text":"The number of innings in a regulation Little League baseball game","response":"6"}]},{"category":"FOOD","comments":"","clues":[{"text":"Traditionally, junket is served for this course","response":"dessert"},{"text":"You can thicken a thin sauce by adding beurre manie, a kneaded mixture of flour &amp; this","response":"butter"},{"text":"Salsify, which is eaten as a vegetable, has another name which tells you it tastes like this mollusk","response":"an oyster"},{"text":"Cumberland sauce, which is often served with game, contains a red jelly made from this fruit","response":"currant"},{"text":"This word, Italian for \"cooked\", describes a type of salami","response":"<i>cotta</i>"}]},{"category":"PRESIDENTIAL RELATIVES","comments":"","clues":[{"text":"This president's farewell to his mother in 1789 is reenacted every Mother's Day in her Virginia home","response":"George Washington"},{"text":"He dropped out of Yale &amp; became a ballet dancer","response":"Ron Reagan Jr."},{"text":"Zachary Taylor was a second cousin of this fourth president","response":"James Madison"},{"text":"He was the first son of a president to become a senator","response":"John Quincy Adams"},{"text":"The first names of 2 of JFK's sisters","response":"(2 of) Eunice & Rosemary (Kathleen, Patricia & Jean)"}]},{"category":"TELEVISION","comments":"","clues":[{"text":"In honor of St. Patrick's Day, the Nickelodeon network tinted 4 episodes of \"My Three Sons\" this color","response":"green"},{"text":"This NBC series' youngest guest host was 7-year-old Drew Barrymore in 1982","response":"<i>Saturday Night Live</i>"},{"text":"Henry Winkler is an executive producer of this series that stars Richard Dean Anderson","response":"<i>MacGyver</i>"},{"text":"When this show about show biz premiered in 1981, R. Chamberlain was the 1st celebrity interviewed","response":"<i>Entertainment Tonight</i>"},{"text":"They were married on <br> \"The Tonight Show\" in 1969","response":"Tiny Tim & Miss Vicki"}]},{"category":"\"OLD\" HAT","comments":"","clues":[{"text":"They \"never die; they just fade away\"","response":"old soldiers"},{"text":"An iced cocktail made with whiskey, a dash of soda, bitters, sweetening &amp; bits of fruit","response":"an old fashioned"},{"text":"Jews divide it into three sections called the law, the prophets &amp; the writings","response":"the Old Testament"},{"text":"Though it was made of wood, the U.S.S. Constitution was called this","response":"\"Old Ironsides\""},{"text":"For his love of formality &amp; flamboyant dress, Winfield Scott's troops called him this","response":"Old Fuss and Feathers"}]}],[{"category":"BODIES OF WATER","comments":"","clues":[{"text":"Bangladesh's coastline extends about 350 miles along this bay","response":"the Bay of Bengal"},{"text":"An arm of the Mediterranean, this sea separates Italy from Yugoslavia","response":"the Adriatic"},{"text":"One of two South American countries that border on the Caribbean Sea","response":"(1 of 2) Venezuela (or Colombia)"},{"text":"You'll find the cities of Florence &amp; Pisa on the banks of this river","response":"the Arno"},{"text":"The French call this strait connecting the North Sea &amp; the English Channel \"Pas de Calais\"","response":"the Strait of Dover"}]},{"category":"QUOTES","comments":"","clues":[{"text":"Campaigning for president, Oct. 24, 1952 in Detroit, he said, \"I shall go to Korea\"","response":"Eisenhower"},{"text":"Jacob Riis' 1890 indictment of slum conditions was titled \"How the Other Half\" does this","response":"Lives"},{"text":"Gelett Burgess wrote of his famous poem about this colorful bovine, \"I'll kill you if you quote it\"","response":"the purple cow"},{"text":"Henry Kissinger called this \"the great aphrodisiac\"","response":"power"},{"text":"Churchill said of Gen. Montgomery, \"In defeat, unbeatable; in victory,\" this","response":"unbearable"}]},{"category":"ART","comments":"","clues":[{"text":"The group of expressionists known as Der Blaue Reiter, or The Blue Rider, formed in this country in 1911","response":"Germany"},{"text":"Of Hedda Hopper, <br>Dennis Hopper or <br>Edward Hopper, the one who painted \"Nighthawks\"","response":"Edward Hopper"},{"text":"The tiny bits of glass &amp; stone used to create this type of art are called tesserae","response":"mosaics"},{"text":"His 1910 painting \"Violin and Pitcher\" is an example of Analytic Cubism, which he &amp; Picasso invented","response":"Georges Braque"},{"text":"Livorno-born 20th-c. artist whose elongated figures reflected his interest in African sculpture","response":"Modigliani"}]},{"category":"BOTANY","comments":"","clues":[{"text":"Ferns reproduce by means of these microscopic cells","response":"spores"},{"text":"The USSR is the top grower of these tall flowers grown for their edible seeds &amp; oil","response":"sunflowers"},{"text":"Diatoms are single-cell varieties of these water plants","response":"algae"},{"text":"The \"L.\" attached to the scientific names of numerous plants refers to this Swedish botanist","response":"(Carolus) Linnaeus"},{"text":"First found as a vine on trees, this plant was given a Greek name meaning \"lover of trees\"","response":"philodendron"}]},{"category":"U.S. HISTORY","comments":"","clues":[{"text":"1857 Supreme Court case that nullified parts of the Missouri Compromise &amp; the Compromise of 1850","response":"the Dred Scott decision"},{"text":"The Triangle Shirtwaist Co. fire in 1911 in this city led to demands for improved working conditions","response":"New York City"},{"text":"It's said this 1925 trial caused William Jennings Bryan's death","response":"the Scopes trial"},{"text":"March 27, 1964 is memorable in Alaskan history for this reason","response":"major earthquake"},{"text":"The Patrons of Husbandry, founded in 1867, were popularly known as this","response":"the Grange"}]},{"category":"LEGENDARY CREATURES","comments":"","clues":[{"text":"In ancient China they came in different colors, &amp; yellow ones were superior","response":"dragons"},{"text":"This bird gathers up the ashes of its former self &amp; carries them to the Egyptian altar of the sun","response":"the Phoenix"},{"text":"Long before Bram Stoker, Alexandre Dumas wrote a play about this kind of creature","response":"a vampire"},{"text":"It was once believed if one of these slips a magic cap on a mortal's head, the human could live undersea","response":"a mermaid"},{"text":"Though this multi-headed monster could grow 2 new heads for each 1 cut off, Hercules slew it","response":"a Hydra"}]}],{"category":"LITERARY CHARACTERS","text":"2 characters in this American classic were named for a king of Israel &amp; the oldest son of Abraham","response":"<i>Moby-Dick</i>"}]}