{"showNumber":2657,"airDate":"1996-03-05","comments":"","rounds":[[{"category":"WORLD CAPITALS","comments":"","clues":[{"text":"The name of this Canadian capital comes from an Indian word meaning \"to trade\"","response":"Ottawa"},{"text":"This Colombian capital is located at an elevation of almost 8,700 feet","response":"Bogota"},{"text":"2 9-hole golf courses serve this capital of Nepal","response":"Kathmandu"},{"text":"This capital on the Tigris River was founded in the 8th century by Caliph Al-Mansur","response":"Baghdad"},{"text":"Suprema a Situ, supreme by situation, is the motto of this New Zealand capital","response":"Wellington"}]},{"category":"CLASSIC TV WESTERNS","comments":"","clues":[{"text":"James Garner &amp; Jack Kelly played brothers Bret &amp; Bart on this ABC western","response":"<i>Maverick</i>"},{"text":"This Chuck Connors series was the most popular new show of the 1958-59 season","response":"<i>The Rifleman</i>"},{"text":"This James Drury title character's real name was never revealed on the show","response":"<i>The Virginian</i>"},{"text":"For 11 seasons Ken Curtis played this hillbilly deputy on \"Gunsmoke\"","response":"Festus"},{"text":"He was the only survivor of an ambush by Butch Cavendish's Hole in the Wall Gang","response":"the Lone Ranger"}]},{"category":"COLORS","comments":"","clues":[{"text":"This shade of yellow is named for a type of pet songbird","response":"canary"},{"text":"Bone can be beige or an off shade of this color","response":"white"},{"text":"This color is named for a plant genus named for 16th century German botanist Leonhard Fuchs","response":"fuchsia"},{"text":"The Persian for \"dust\" gave us the name of this dull brown often used for military uniforms","response":"khaki"},{"text":"This deep blue dye once came from a member of the pea family grown on southern plantations","response":"indigo"}]},{"category":"FURNITURE","comments":"","clues":[{"text":"Woolens, etc. are stored in a cedar chest for protection from these pests","response":"moths"},{"text":"\"Optimistic\" term for the chest used to store one's trousseau","response":"a hope chest"},{"text":"This child's bed mounted on rockers has nearly been replaced by the more functional crib","response":"a cradle"},{"text":"Biedermeier, a 19th century style from this country, got its name from a bourgeois caricature","response":"Germany"},{"text":"A cabriole is this part of a piece of furniture shaped in a double curve","response":"the legs"}]},{"category":"BIBLE QUOTATIONS","comments":"","clues":[{"text":"Proverbs says, \"Pride goeth before destruction, and an haughty spirit before\" this","response":"a fall"},{"text":"\"Cast\" this \"upon the waters: for thou shalt find it after many days\"","response":"your bread"},{"text":"In the Old Testament, praying for deliverance, he said, \"The waters compassed me about, even to the soul\"","response":"Jonah"},{"text":"Patriarch to whom God said, \"Thou shalt go to thy fathers in peace; thou shalt be buried in a good old age\"","response":"Abraham"},{"text":"He was asked, \"Art thou able to make known unto me the dream which I have seen...?\"","response":"Daniel"}]},{"category":"7-LETTER WORDS","comments":"","clues":[{"text":"Grasse, France is an important supplier of flowers used to make this fragrant fluid","response":"perfume"},{"text":"If you \"go off on\" one of these, you've changed course or made a sudden digression","response":"a tangent"},{"text":"This word can mean agreement, or a musical performance","response":"a concert"},{"text":"A costumed procession, or a show consisting of beauty contestants","response":"a pageant"},{"text":"The Greek for \"learned man\" gave us this term for a record of past events or the study of them","response":"history"}]}],[{"category":"HISTORIC WOMEN","comments":"","clues":[{"text":"She was about 12 years old when she saved the life of Captain John Smith","response":"Pocahontas"},{"text":"The subject of a rhyme, she was acquitted of a double murder in 1893","response":"Lizzie Borden"},{"text":"In 1899, at her own Paris theatre, she gave the first of her famous performances as Hamlet","response":"Sarah Bernhardt"},{"text":"This infamous Italian patron of the arts was the illegitimate daughter of the future Pope Alexander VI","response":"Lucrezia Borgia"},{"text":"In 1927 this American birth control pioneer helped organize the first world population conference","response":"(Margaret) Sanger"}]},{"category":"CHEMISTRY","comments":"","clues":[{"text":"Hold a lump of gallium in your hand &amp; it will do this, so you can assume M&M's aren't coated with it","response":"melt"},{"text":"The name of this gas, NH<sub>3</sub>, goes back to ancient Egypt, where it was part of the salt of Ammon","response":"Ammonia"},{"text":"A \"strong\" one of these, like sulfuric or hydrochloric, will ionize completely in water","response":"An acid"},{"text":"For osmosis to occur, you need a semipermeable one of these between the 2 solutions","response":"a membrane"},{"text":"In the process of sublimation, this state of matter is skipped","response":"liquid"}]},{"category":"COMPOSERS","comments":"","clues":[{"text":"1790's \"Cosi Fan Tutte\" was his first opera commission since 1787's \"Don Giovanni\"","response":"Mozart"},{"text":"John Cage's \"Prepared\" type of this keyboard instrument has objects attached to the strings","response":"a piano"},{"text":"This author of \"A Clockwork Orange\" wrote the 3-movement \"Sinfoni Melayu\", based on Malaysian themes","response":"Burgess"},{"text":"In 1865 Anton Bruckner attended the premiere of \"Tristan und Isolde\" &amp; met this man, its composer","response":"Wagner"},{"text":"Liszt's piano music was influenced by the phenomenal technique of this Italian violin virtuoso","response":"Paganini"}]},{"category":"NATIONAL MONUMENTS","comments":"","clues":[{"text":"In 1939 this Baltimore fort's status was changed from National Park to National Monument","response":"Fort McHenry"},{"text":"Virginia has 2 national monuments: the birthplaces of George Washington &amp; this black educator","response":"Booker T. Washington"},{"text":"Devils Postpile National Monument is in California &amp; Devils Tower is found in this state","response":"Wyoming"},{"text":"This expanse of gypsum dunes lies between the San Andres &amp; Sacramento Mountains in New Mexico","response":"White Sands National Monument"},{"text":"A monument on San Diego Bay honors this Portuguese explorer who claimed the west coast for Spain","response":"Juan Cabrillo"}]},{"category":"POLITICS","comments":"","clues":[{"text":"The Democratic Party used a hickory pole &amp; broom and a rooster as emblems before settling on this","response":"a donkey"},{"text":"This senator popularized the phrase \"Point of order\" at 1954 Senate hearings","response":"(Joe) McCarthy"},{"text":"Lord Acton said this \"tends to corrupt\"","response":"power"},{"text":"Popular name of the States' Rights Democrats who supported Strom Thurmond in 1948","response":"the Dixiecrats"},{"text":"This term for an intermediary between citizen &amp; government comes from the Swedish for \"Commissioner\"","response":"ombudsman"}]},{"category":"LITERATURE","comments":"","clues":[{"text":"This 1950 Ray Bradbury novel about life on Mars was titled \"The Silver Locusts\" in England","response":"<i>The Martian Chronicles</i>"},{"text":"This Herman Melville title character, an English sailor, is hanged for killing master-at-arms Claggart","response":"Billy Budd"},{"text":"In the Jonathan Swift novel, it's Gulliver's first name","response":"Lemuel"},{"text":"Floral Heights, a suburb of this fictional metropolis, is the setting for Sinclair Lewis' \"Babbitt\"","response":"Zenith"},{"text":"The title of this William Faulkner novel refers to 3 friends who steal a banker's car","response":"<i>The Reivers</i>"}]}],{"category":"THE OSCARS","text":"Husband &amp; wife who were both nominated for playing a married couple in a 1966 film; only the wife won","response":"Richard Burton & Elizabeth Taylor"}]}